[
{
"id":"1",
"deptName":"天津事业部",
"parentId":"6",
"deptParent":"软通动力集团",
"desc":"",
"enable":"1"
},
{
"id":"2",
"deptName":"北京事业部",
"parentId":"6",
"deptParent":"软通动力集团",
"desc":"",
"enable":"1"
},
{
"id":"3",
"deptName":"金融事业部",
"parentId":"6",
"deptParent":"软通动力集团",
"desc":"",
"enable":"1"
},
{
"id":"4",
"deptName":"外包事业部",
"parentId":"6",
"deptParent":"软通动力集团",
"desc":"",
"enable":"1"
},
{
"id":"5",
"deptName":"财务部",
"parentId":"6",
"deptParent":"软通动力集团",
"desc":"",
"enable":"1"
},
{
"id":"6",
"deptName":"软通动力集团",
"parentId":"",
"deptParent":"",
"desc":"",
"enable":"1"
},
{
"id":"7",
"deptName":"人力资源办公室",
"parentId":"6",
"deptParent":"软通动力集团",
"desc":"",
"enable":"1"
},
{
"id":"8",
"deptName":"开发事业1部",
"parentId":"1",
"deptParent":"天津事业部",
"desc":"",
"enable":"1"
},
{
"id":"9",
"deptName":"开发事业2部",
"parentId":"1",
"deptParent":"天津事业部",
"desc":"",
"enable":"1"
},
{
"id":"10",
"deptName":"开发事业3部",
"parentId":"2",
"deptParent":"北京事业部",
"desc":"",
"enable":"1"
},
{
"id":"11",
"deptName":"开发事业4部",
"parentId":"2",
"deptParent":"北京事业部",
"desc":"",
"enable":"1"
},
{
"id":"12",
"deptName":"金融服务部",
"parentId":"3",
"deptParent":"金融事业部",
"desc":"",
"enable":"1"
},
{
"id":"13",
"deptName":"金融创新部",
"parentId":"3",
"deptParent":"金融事业部",
"desc":"",
"enable":"1"
}
]